lea/__init__.py
lea/cli.py
lea/comment.py
lea/conductor.py
lea/dag.py
lea/databases.py
lea/dialects.py
lea/field.py
lea/job.py
lea/scripts.py
lea/session.py
lea/table_ref.py
lea/test_big_query.py
lea/test_duckdb.py
lea/test_table_ref.py
lea/assertions/NO_NULLS.sql.jinja
lea/assertions/SET.sql.jinja
lea/assertions/UNIQUE.sql.jinja
lea/assertions/UNIQUE_BY.sql.jinja
lea_cli-0.16.0.dist-info/METADATA
lea_cli-0.16.0.dist-info/WHEEL
lea_cli-0.16.0.dist-info/entry_points.txt
lea_cli-0.16.0.dist-info/licenses/LICENSE
lea_cli-0.16.0.dist-info/RECORD
