Metadata-Version: 2.4
Name: lea-cli
Version: 0.16.0
Summary: A minimalist alternative to dbt
Author-email: Max Halford <maxhalford25@gmail.com>
License-File: LICENSE
Requires-Python: <4,>=3.11
Requires-Dist: click<9,>=8.1.7
Requires-Dist: db-dtypes<2,>=1.1.1
Requires-Dist: duckdb<2,>=1.3.0
Requires-Dist: filelock<4,>=3.20.1
Requires-Dist: gitpython<4,>=3.1.43
Requires-Dist: google-cloud-bigquery-storage<3,>=2.27.0
Requires-Dist: google-cloud-bigquery<4,>=3.11.4
Requires-Dist: jinja2<4,>=3.1.2
Requires-Dist: pandas<3,>=2.1.3
Requires-Dist: python-dotenv<2,>=1.0.0
Requires-Dist: pyyaml<7,>=6
Requires-Dist: requests<3,>=2.32.3
Requires-Dist: rich<15,>=13.5.3
Requires-Dist: rsa<5,>=4.7
Requires-Dist: sqlglot<29,>=27.8
